e3v3se_display/TJC3224.py
e3v3se_display/__init__.py
e3v3se_display/display_interface.py
e3v3se_display/e3v3se_display.py
e3v3se_display/encoder.py
e3v3se_display/printerInterface.py
e3v3se_display/run.py
e3v3se_display/serial_port_manager.py
e3v3se_display/virtual_encoder.py
e3v3se_display_klipper-1.0.dist-info/LICENSE
e3v3se_display_klipper-1.0.dist-info/METADATA
e3v3se_display_klipper-1.0.dist-info/WHEEL
e3v3se_display_klipper-1.0.dist-info/entry_points.txt
e3v3se_display_klipper-1.0.dist-info/top_level.txt
e3v3se_display_klipper-1.0.dist-info/RECORD
