Metadata-Version: 2.1
Name: e3v3se-display-klipper
Version: 1.0
Summary: UNKNOWN
Home-page: UNKNOWN
License: UNKNOWN
Platform: UNKNOWN
Requires-Dist: argparse
Requires-Dist: configparser
Requires-Dist: multitimer
Requires-Dist: pyserial
Requires-Dist: requests
Requires-Dist: websocket-client
